{
  "id": "mie-305",
  "slug": "mie-305",
  "title": "MIE 305 — Legal and Regulatory Environment of Business",
  "description": "The legal and regulatory environment of business operations. Covers contracts, torts, property, intellectual property, business organizations, agency, constitutional law, administrative law, criminal law, ethics, and legal risk management.",
  "subject": "Business Law",
  "level": "beginner",
  "units": [
    {
      "id": "u1",
      "title": "Unit 1: Foundations of Law and the Legal Environment",
      "topics": [
        { "id": "t1", "slug": "functions-and-sources-of-law", "title": "Functions and Sources of Law" },
        { "id": "t2", "slug": "common-law-legal-reasoning", "title": "Common-Law Legal Reasoning" },
        { "id": "t3", "slug": "classifications-of-law", "title": "Classifications of Law" },
        { "id": "t4", "slug": "jurisprudence-and-legal-philosophy", "title": "Jurisprudence and Legal Philosophy" },
        { "id": "t5", "slug": "legal-terminology", "title": "Legal Terminology" }
      ]
    },
    {
      "id": "u2",
      "title": "Unit 2: Ethics, Corporate Responsibility, and Legal Risk",
      "topics": [
        { "id": "t6", "slug": "law-versus-ethics", "title": "Law Versus Ethics" },
        { "id": "t7", "slug": "ethical-frameworks", "title": "Major Ethical Frameworks" },
        { "id": "t8", "slug": "stakeholders-and-corporate-responsibility", "title": "Stakeholders and Corporate Responsibility" },
        { "id": "t9", "slug": "ethical-decision-making", "title": "Ethical Decision-Making" },
        { "id": "t10", "slug": "compliance-and-legal-risk-management", "title": "Compliance and Legal Risk Management" }
      ]
    },
    {
      "id": "u3",
      "title": "Unit 3: The Court System and Jurisdiction",
      "topics": [
        { "id": "t11", "slug": "court-systems", "title": "State and Federal Court Systems" },
        { "id": "t12", "slug": "subject-matter-jurisdiction", "title": "Subject-Matter Jurisdiction" },
        { "id": "t13", "slug": "personal-jurisdiction", "title": "Personal Jurisdiction" },
        { "id": "t14", "slug": "venue", "title": "Venue" },
        { "id": "t15", "slug": "standing-and-justiciability", "title": "Standing and Justiciability" }
      ]
    },
    {
      "id": "u4",
      "title": "Unit 4: Civil Procedure and Alternative Dispute Resolution",
      "topics": [
        { "id": "t16", "slug": "beginning-a-civil-lawsuit", "title": "Beginning a Civil Lawsuit" },
        { "id": "t17", "slug": "pretrial-procedure", "title": "Pretrial Procedure" },
        { "id": "t18", "slug": "trial-procedure", "title": "Trial Procedure" },
        { "id": "t19", "slug": "appeals", "title": "Appeals" },
        { "id": "t20", "slug": "remedies", "title": "Remedies" },
        { "id": "t21", "slug": "alternative-dispute-resolution", "title": "Alternative Dispute Resolution" }
      ]
    },
    {
      "id": "u5",
      "title": "Unit 5: Constitutional Law in Business",
      "topics": [
        { "id": "t22", "slug": "structure-of-the-constitution", "title": "Structure of the Constitution" },
        { "id": "t23", "slug": "commerce-clause", "title": "Commerce Clause" },
        { "id": "t24", "slug": "supremacy-and-preemption", "title": "Supremacy and Preemption" },
        { "id": "t25", "slug": "first-amendment-and-business", "title": "First Amendment and Business" },
        { "id": "t26", "slug": "due-process", "title": "Due Process" },
        { "id": "t27", "slug": "equal-protection", "title": "Equal Protection" },
        { "id": "t28", "slug": "takings-clause", "title": "Takings Clause" }
      ]
    },
    {
      "id": "u6",
      "title": "Unit 6: Administrative Law and Regulation",
      "topics": [
        { "id": "t29", "slug": "administrative-agencies", "title": "Administrative Agencies" },
        { "id": "t30", "slug": "agency-functions", "title": "Agency Functions" },
        { "id": "t31", "slug": "rulemaking", "title": "Rulemaking" },
        { "id": "t32", "slug": "agency-investigations-and-enforcement", "title": "Agency Investigations and Enforcement" },
        { "id": "t33", "slug": "administrative-hearings-and-judicial-review", "title": "Administrative Hearings and Judicial Review" },
        { "id": "t34", "slug": "major-business-regulators", "title": "Major Business Regulators" }
      ]
    },
    {
      "id": "u7",
      "title": "Unit 7: Tort Law Foundations",
      "topics": [
        { "id": "t35", "slug": "purpose-of-tort-law", "title": "Purpose and Structure of Tort Law" },
        { "id": "t36", "slug": "intent-and-transferred-intent", "title": "Intent and Transferred Intent" },
        { "id": "t37", "slug": "tort-defenses-and-privileges", "title": "Defenses and Privileges" },
        { "id": "t38", "slug": "tort-damages", "title": "Tort Damages" }
      ]
    },
    {
      "id": "u8",
      "title": "Unit 8: Intentional Torts and Business Torts",
      "topics": [
        { "id": "t39", "slug": "torts-against-persons", "title": "Torts Against Persons" },
        { "id": "t40", "slug": "defamation", "title": "Defamation" },
        { "id": "t41", "slug": "privacy-torts", "title": "Privacy Torts" },
        { "id": "t42", "slug": "torts-involving-property", "title": "Torts Involving Property" },
        { "id": "t43", "slug": "business-and-economic-torts", "title": "Business and Economic Torts" },
        { "id": "t44", "slug": "misrepresentation-and-fraud", "title": "Misrepresentation and Fraud" }
      ]
    },
    {
      "id": "u9",
      "title": "Unit 9: Negligence",
      "topics": [
        { "id": "t45", "slug": "elements-of-negligence", "title": "Elements of Negligence" },
        { "id": "t46", "slug": "duty-of-care", "title": "Duty of Care" },
        { "id": "t47", "slug": "breach", "title": "Breach" },
        { "id": "t48", "slug": "actual-causation", "title": "Actual Causation" },
        { "id": "t49", "slug": "proximate-causation", "title": "Proximate Causation" },
        { "id": "t50", "slug": "negligence-damages", "title": "Damages in Negligence" },
        { "id": "t51", "slug": "negligence-defenses", "title": "Defenses to Negligence" }
      ]
    },
    {
      "id": "u10",
      "title": "Unit 10: Strict Liability and Product Liability",
      "topics": [
        { "id": "t52", "slug": "strict-liability", "title": "Strict Liability" },
        { "id": "t53", "slug": "product-liability-theories", "title": "Product Liability Theories" },
        { "id": "t54", "slug": "product-defects", "title": "Product Defects" },
        { "id": "t55", "slug": "product-liability-parties-and-defenses", "title": "Parties and Defenses in Product Liability" },
        { "id": "t56", "slug": "product-liability-risk-management", "title": "Product Liability Risk Management" }
      ]
    },
    {
      "id": "u11",
      "title": "Unit 11: Criminal Law and Business",
      "topics": [
        { "id": "t57", "slug": "criminal-law-foundations", "title": "Criminal Law Foundations" },
        { "id": "t58", "slug": "elements-of-crimes", "title": "Elements of Crimes" },
        { "id": "t59", "slug": "white-collar-crimes", "title": "Business and White-Collar Crimes" },
        { "id": "t60", "slug": "corporate-criminal-liability", "title": "Corporate and Managerial Liability" },
        { "id": "t61", "slug": "constitutional-protections-criminal", "title": "Constitutional Protections in Criminal Law" },
        { "id": "t62", "slug": "sentencing-and-compliance", "title": "Sentencing and Compliance" }
      ]
    },
    {
      "id": "u12",
      "title": "Unit 12: Contract Formation",
      "topics": [
        { "id": "t63", "slug": "contract-classifications", "title": "Contract Classifications" },
        { "id": "t64", "slug": "offer", "title": "Offer" },
        { "id": "t65", "slug": "acceptance", "title": "Acceptance" },
        { "id": "t66", "slug": "consideration", "title": "Consideration" },
        { "id": "t67", "slug": "mutual-assent", "title": "Mutual Assent" }
      ]
    },
    {
      "id": "u13",
      "title": "Unit 13: Contract Defenses and Enforceability",
      "topics": [
        { "id": "t68", "slug": "capacity", "title": "Capacity" },
        { "id": "t69", "slug": "legality", "title": "Legality" },
        { "id": "t70", "slug": "mistake", "title": "Mistake" },
        { "id": "t71", "slug": "misrepresentation-in-contracts", "title": "Misrepresentation and Fraud in Contracts" },
        { "id": "t72", "slug": "duress-and-undue-influence", "title": "Duress and Undue Influence" },
        { "id": "t73", "slug": "statute-of-frauds", "title": "Statute of Frauds" },
        { "id": "t74", "slug": "parol-evidence", "title": "Parol Evidence Rule" }
      ]
    },
    {
      "id": "u14",
      "title": "Unit 14: Contract Performance, Breach, and Remedies",
      "topics": [
        { "id": "t75", "slug": "conditions", "title": "Conditions" },
        { "id": "t76", "slug": "performance-and-breach", "title": "Performance and Breach" },
        { "id": "t77", "slug": "discharge", "title": "Discharge of Contracts" },
        { "id": "t78", "slug": "anticipatory-repudiation", "title": "Anticipatory Repudiation" },
        { "id": "t79", "slug": "contract-damages", "title": "Contract Damages" },
        { "id": "t80", "slug": "liquidated-damages", "title": "Liquidated Damages and Penalties" },
        { "id": "t81", "slug": "equitable-remedies", "title": "Equitable Remedies" }
      ]
    },
    {
      "id": "u15",
      "title": "Unit 15: Third-Party Contract Rights",
      "topics": [
        { "id": "t82", "slug": "assignment", "title": "Assignment" },
        { "id": "t83", "slug": "delegation", "title": "Delegation" },
        { "id": "t84", "slug": "novation", "title": "Novation" },
        { "id": "t85", "slug": "third-party-beneficiaries", "title": "Third-Party Beneficiaries" }
      ]
    },
    {
      "id": "u16",
      "title": "Unit 16: Sales and Leases Under the UCC",
      "topics": [
        { "id": "t86", "slug": "scope-of-article-2", "title": "Scope of UCC Article 2" },
        { "id": "t87", "slug": "ucc-contract-formation", "title": "UCC Contract Formation" },
        { "id": "t88", "slug": "title-and-risk-of-loss", "title": "Title and Risk of Loss" },
        { "id": "t89", "slug": "ucc-performance", "title": "Performance Under the UCC" },
        { "id": "t90", "slug": "warranties", "title": "Warranties" },
        { "id": "t91", "slug": "ucc-remedies", "title": "Buyer and Seller Remedies Under the UCC" }
      ]
    },
    {
      "id": "u17",
      "title": "Unit 17: Agency Law",
      "topics": [
        { "id": "t92", "slug": "creating-agency-relationship", "title": "Creating an Agency Relationship" },
        { "id": "t93", "slug": "agent-duties", "title": "Agent's Duties" },
        { "id": "t94", "slug": "principal-duties", "title": "Principal's Duties" },
        { "id": "t95", "slug": "authority", "title": "Authority" },
        { "id": "t96", "slug": "contract-liability-agency", "title": "Contract Liability in Agency" },
        { "id": "t97", "slug": "tort-liability-agency", "title": "Tort Liability in Agency" },
        { "id": "t98", "slug": "termination-of-agency", "title": "Termination of Agency" }
      ]
    },
    {
      "id": "u18",
      "title": "Unit 18: Business Organizations",
      "topics": [
        { "id": "t99", "slug": "sole-proprietorship", "title": "Sole Proprietorship" },
        { "id": "t100", "slug": "general-partnership", "title": "General Partnership" },
        { "id": "t101", "slug": "limited-partnerships", "title": "Limited Partnerships" },
        { "id": "t102", "slug": "limited-liability-companies", "title": "Limited Liability Companies" },
        { "id": "t103", "slug": "corporations", "title": "Corporations" },
        { "id": "t104", "slug": "corporate-authority-and-governance", "title": "Corporate Authority and Governance" },
        { "id": "t105", "slug": "fiduciary-duties", "title": "Fiduciary Duties" },
        { "id": "t106", "slug": "piercing-the-corporate-veil", "title": "Piercing the Corporate Veil" },
        { "id": "t107", "slug": "comparing-entity-choices", "title": "Comparing Entity Choices" }
      ]
    },
    {
      "id": "u19",
      "title": "Unit 19: Property Law",
      "topics": [
        { "id": "t108", "slug": "property-classifications", "title": "Property Classifications" },
        { "id": "t109", "slug": "ownership-and-possession", "title": "Ownership and Possession" },
        { "id": "t110", "slug": "real-property-interests", "title": "Real Property Interests" },
        { "id": "t111", "slug": "landlord-tenant-basics", "title": "Landlord-Tenant Basics" },
        { "id": "t112", "slug": "bailments", "title": "Bailments" }
      ]
    },
    {
      "id": "u20",
      "title": "Unit 20: Intellectual Property",
      "topics": [
        { "id": "t113", "slug": "patents", "title": "Patents" },
        { "id": "t114", "slug": "copyright", "title": "Copyright" },
        { "id": "t115", "slug": "trademarks", "title": "Trademarks" },
        { "id": "t116", "slug": "trade-secrets", "title": "Trade Secrets" },
        { "id": "t117", "slug": "comparing-ip-protections", "title": "Comparing IP Protections" },
        { "id": "t118", "slug": "online-and-ai-ip-issues", "title": "Online and AI-Related IP Issues" }
      ]
    },
    {
      "id": "u21",
      "title": "Unit 21: Employment and Workplace Law",
      "topics": [
        { "id": "t119", "slug": "employment-relationships", "title": "Employment Relationships" },
        { "id": "t120", "slug": "wage-and-hour-regulation", "title": "Wage and Hour Regulation" },
        { "id": "t121", "slug": "workplace-safety", "title": "Workplace Safety" },
        { "id": "t122", "slug": "employment-discrimination", "title": "Employment Discrimination" },
        { "id": "t123", "slug": "workplace-privacy", "title": "Workplace Privacy" },
        { "id": "t124", "slug": "employee-duties-and-restrictive-agreements", "title": "Employee Duties and Restrictive Agreements" }
      ]
    },
    {
      "id": "u22",
      "title": "Unit 22: Consumer Protection, Competition, and Securities",
      "topics": [
        { "id": "t125", "slug": "consumer-protection", "title": "Consumer Protection" },
        { "id": "t126", "slug": "antitrust-fundamentals", "title": "Antitrust Fundamentals" },
        { "id": "t127", "slug": "securities-regulation", "title": "Securities Regulation" },
        { "id": "t128", "slug": "business-compliance", "title": "Business Compliance" }
      ]
    },
    {
      "id": "u23",
      "title": "Unit 23: International Legal Environment",
      "topics": [
        { "id": "t129", "slug": "sovereignty-and-jurisdiction", "title": "Sovereignty and Jurisdiction" },
        { "id": "t130", "slug": "international-contracts", "title": "International Contracts" },
        { "id": "t131", "slug": "international-institutions", "title": "International Institutions and Agreements" },
        { "id": "t132", "slug": "international-compliance-risks", "title": "International Compliance Risks" },
        { "id": "t133", "slug": "legal-system-differences", "title": "Legal System Differences" }
      ]
    }
  ]
}
